LICENSE
README.rst
setup.py
custom_handlers/__init__.py
custom_handlers/logging_handlers.py
custom_handlers/messaging_handlers.py
external_logging_handlers.egg-info/PKG-INFO
external_logging_handlers.egg-info/SOURCES.txt
external_logging_handlers.egg-info/dependency_links.txt
external_logging_handlers.egg-info/requires.txt
external_logging_handlers.egg-info/top_level.txt