Metadata-Version: 2.1
Name: external-logging-handlers
Version: 0.1.4
Summary: Custom handlers for standard logging module
Home-page: https://github.com/alexvoksa/logging-handlers
Author: Alexander
Author-email: bf-109g@yandex.ru
License: MIT License
Platform: UNKNOWN
Requires-Python: >=3.9.1
License-File: LICENSE
